{
  "years": ["FY21", "FY22", "FY23", "FY24", "FY25"],
  "companies": [
    {
      "name": "Reliance Industries",
      "ticker": "RELIANCE",
      "sector": "Oil & Gas",
      "revenue":         [466307, 694673, 876396, 899041, 962820],
      "profit":          [53739,  67845,  74088,  79020,  81309],
      "cfo":             [26958,  110654, 115032, 158788, 178703],
      "debt":            [278962, 319158, 451664, 350719, 374313],
      "promoterHolding": [50.58,  50.66,  50.41,  50.31,  50.10]
    },
    {
      "name": "HDFC Bank",
      "ticker": "HDFCBANK",
      "sector": "Banking",
      "revenue":         [128552, 135936, 170754, 283649, 336367],
      "profit":          [31857,  38151,  46149,  65446,  73440],
      "cfo":             [42476,  -11960, 20814,  19069,  127242],
      "debt":            [177697, 226966, 256549, 730615, 634606],
      "promoterHolding": [25.97,  25.78,  25.59,  0.00,   0.00]
    },
    {
      "name": "Infosys",
      "ticker": "INFY",
      "sector": "Information Technology",
      "revenue":         [100472, 121641, 146767, 153670, 162990],
      "profit":          [19423,  22146,  24108,  26248,  26750],
      "cfo":             [23224,  23885,  22467,  25210,  35694],
      "debt":            [5325,   5474,   8299,   8359,   8227],
      "promoterHolding": [12.95,  13.11,  15.14,  14.71,  14.60]
    },
    {
      "name": "Hindustan Unilever",
      "ticker": "HINDUNILVR",
      "sector": "FMCG",
      "revenue":         [47028,  52446,  60580,  61896,  63121],
      "profit":          [7999,   8892,   10143,  10282,  10671],
      "cfo":             [9163,   9048,   9991,   15469,  11886],
      "debt":            [0,      1043,   1219,   1484,   1648],
      "promoterHolding": [61.90,  61.90,  61.90,  61.90,  61.90]
    },
    {
      "name": "Maruti Suzuki India",
      "ticker": "MARUTI",
      "sector": "Automobile",
      "revenue":         [70372,  88330,  117571, 141858, 152913],
      "profit":          [4389,   3880,   8211,   13488,  14500],
      "cfo":             [8856,   1840,   9251,   16801,  16136],
      "debt":            [541,    426,    1247,   119,    87],
      "promoterHolding": [56.37,  56.37,  56.48,  58.19,  58.28]
    },
    {
      "name": "Sun Pharmaceutical Industries",
      "ticker": "SUNPHARMA",
      "sector": "Pharmaceuticals",
      "revenue":         [33498,  38654,  43886,  48497,  52578],
      "profit":          [2272,   3389,   8513,   9610,   10965],
      "cfo":             [6170,   8985,   4959,   12135,  14072],
      "debt":            [3869,   1290,   6886,   3274,   2362],
      "promoterHolding": [54.48,  54.48,  54.48,  54.48,  54.48]
    },
    {
      "name": "Larsen & Toubro",
      "ticker": "LT",
      "sector": "Construction",
      "revenue":         [135979, 156521, 183341, 221113, 255734],
      "profit":          [12921,  10419,  12531,  15547,  17673],
      "cfo":             [23074,  19164,  22777,  18266,  9161],
      "debt":            [134629, 125508, 120650, 116322, 132409],
      "promoterHolding": [0.00,   0.00,   0.00,   0.00,   0.00]
    },
    {
      "name": "Bharti Airtel",
      "ticker": "BHARTIARTL",
      "sector": "Telecom",
      "revenue":         [100616, 116547, 139145, 149982, 172985],
      "profit":          [-12364, 8305,   12287,  8558,   37481],
      "cfo":             [48205,  55017,  65325,  78898,  98332],
      "debt":            [162785, 169678, 226020, 215592, 213642],
      "promoterHolding": [55.86,  55.93,  55.02,  53.48,  52.42]
    },
    {
      "name": "Asian Paints",
      "ticker": "ASIANPAINT",
      "sector": "Paints",
      "revenue":         [21713,  29101,  34489,  35495,  33906],
      "profit":          [3207,   3085,   4195,   5558,   3710],
      "cfo":             [3683,   986,    4193,   6104,   4424],
      "debt":            [1093,   1587,   1933,   2474,   2290],
      "promoterHolding": [52.79,  52.63,  52.63,  52.63,  52.63]
    },
    {
      "name": "NTPC",
      "ticker": "NTPC",
      "sector": "Power",
      "revenue":         [111531, 132669, 176207, 178525, 188138],
      "profit":          [14635,  16676,  17121,  21332,  23953],
      "cfo":             [32444,  41788,  47152,  40099,  50436],
      "debt":            [210208, 210707, 222913, 237131, 250096],
      "promoterHolding": [51.10,  51.10,  51.10,  51.10,  51.10]
    },
    {
      "name": "Tata Consultancy Services",
      "ticker": "TCS",
      "sector": "Information Technology",
      "revenue":         [164177, 191754, 225458, 240893, 255324],
      "profit":          [32430,  38327,  42147,  45908,  48553],
      "cfo":             [38802,  39548,  41965,  44338,  48000],
      "debt":            [7677,   7565,   8131,   7956,   8200],
      "promoterHolding": [72.05,  72.19,  72.30,  71.77,  71.77]
    },
    {
      "name": "Tata Steel",
      "ticker": "TATASTEEL",
      "sector": "Metals & Mining",
      "revenue":         [156477, 243959, 243353, 229171, 218543],
      "profit":          [8190,   41749,  8075,   -4910,  3174],
      "cfo":             [31905,  42283,  25000,  26796,  29850],
      "debt":            [88501,  76000,  71477,  81000,  78250],
      "promoterHolding": [34.39,  33.90,  33.19,  33.19,  33.19]
    },
    {
      "name": "ICICI Bank",
      "ticker": "ICICIBANK",
      "sector": "Banking",
      "revenue":         [89163,  95407,  121067, 159516, 186331],
      "profit":          [20364,  26538,  35461,  46081,  54569],
      "cfo":             [138015, 58111,  -3771,  157284, 122805],
      "debt":            [143900, 161603, 189062, 207428, 218883],
      "promoterHolding": [0.00,   0.00,   0.00,   0.00,   0.00]
    },
    {
      "name": "State Bank of India",
      "ticker": "SBIN",
      "sector": "Banking",
      "revenue":         [278115, 289973, 350845, 439189, 490938],
      "profit":          [23888,  37183,  57750,  69543,  80523],
      "cfo":             [89919,  57695,  -86014, 21632,  48486],
      "debt":            [433796, 449160, 521152, 639610, 610857],
      "promoterHolding": [57.63,  57.59,  57.49,  57.54,  57.43]
    },
    {
      "name": "Axis Bank",
      "ticker": "AXISBANK",
      "sector": "Banking",
      "revenue":         [64397,  68846,  87448,  112759, 127374],
      "profit":          [7252,   14207,  10919,  26492,  28191],
      "cfo":             [12633,  28137,  22075,  -5555,  44384],
      "debt":            [152249, 199778, 206214, 228200, 220687],
      "promoterHolding": [13.58,  9.70,   8.16,   8.22,   8.18]
    },
    {
      "name": "Bajaj Finance",
      "ticker": "BAJFINANCE",
      "sector": "NBFC",
      "revenue":         [26673,  31641,  41411,  54974,  69709],
      "profit":          [4420,   7028,   11508,  14451,  16779],
      "cfo":             [-807,   -37090, -42112, -69843, -68154],
      "debt":            [131634, 165232, 216690, 293346, 361249],
      "promoterHolding": [56.12,  55.86,  55.91,  54.69,  54.73]
    },
    {
      "name": "Mahindra & Mahindra",
      "ticker": "M&M",
      "sector": "Automobile",
      "revenue":         [74278,  90171,  121269, 139078, 159211],
      "profit":          [1512,   7253,   11374,  12270,  14073],
      "cfo":             [17909,  9248,   -7074,  -5630,  3176],
      "debt":            [80625,  77605,  92247,  108647, 129025],
      "promoterHolding": [19.45,  19.47,  19.37,  18.58,  18.45]
    },
    {
      "name": "Tata Motors",
      "ticker": "TATAMOTORS",
      "sector": "Automobile",
      "revenue":         [249795, 278454, 345967, 434016, 439695],
      "profit":          [-13395, -11309, 2690,   31807,  28149],
      "cfo":             [29001,  14283,  35388,  67915,  63102],
      "debt":            [142131, 146449, 134113, 107264, 71540],
      "promoterHolding": [46.41,  46.40,  46.39,  46.36,  42.58]
    },
    {
      "name": "ITC",
      "ticker": "ITC",
      "sector": "FMCG",
      "revenue":         [49257,  60645,  70919,  67932,  75323],
      "profit":          [13383,  15503,  19477,  20751,  35052],
      "cfo":             [12527,  15776,  18878,  17179,  17627],
      "debt":            [271,    249,    306,    303,    285],
      "promoterHolding": [0.00,   0.00,   0.00,   0.00,   0.00]
    },
    {
      "name": "Nestle India",
      "ticker": "NESTLEIND",
      "sector": "FMCG",
      "revenue":         [13350,  14741,  16897,  19126,  20202],
      "profit":          [2082,   2118,   2391,   2999,   3314],
      "cfo":             [2454,   2236,   2737,   3392,   2936],
      "debt":            [147,    266,    271,    271,    1167],
      "promoterHolding": [62.76,  62.76,  62.76,  62.76,  62.76]
    },
    {
      "name": "HCL Technologies",
      "ticker": "HCLTECH",
      "sector": "Information Technology",
      "revenue":         [75379,  85651,  101456, 109913, 117055],
      "profit":          [11169,  13523,  14845,  15710,  17399],
      "cfo":             [19618,  16900,  18009,  22448,  22261],
      "debt":            [6864,   6343,   4794,   5758,   6276],
      "promoterHolding": [60.33,  60.72,  60.82,  60.82,  60.82]
    },
    {
      "name": "Hindalco Industries",
      "ticker": "HINDALCO",
      "sector": "Metals & Mining",
      "revenue":         [132008, 195059, 223202, 215962, 238496],
      "profit":          [3483,   13730,  10097,  10155,  16002],
      "cfo":             [67206,  64486,  60291,  56356,  63929],
      "debt":            [67206,  64486,  60291,  56356,  63929],
      "promoterHolding": [34.64,  34.65,  34.65,  34.65,  34.65]
    }
  ]
}